cv2_ext/__init__.py
opencv_utf_8-0.0.5.dist-info/LICENSE
opencv_utf_8-0.0.5.dist-info/METADATA
opencv_utf_8-0.0.5.dist-info/WHEEL
opencv_utf_8-0.0.5.dist-info/top_level.txt
opencv_utf_8-0.0.5.dist-info/RECORD
