Metadata-Version: 2.1
Name: opencv-utf-8
Version: 0.0.5
Summary: Support opencv read and write image using utf-8 paths
Home-page: https://github.com/azzhu/opencv-utf-8
Author: azzhu
Author-email: zhu.qingjie@qq.com
License: MIT
Project-URL: Source Code, https://github.com/azzhu/opencv-utf-8
Project-URL: Bug Tracker, https://github.com/azzhu/opencv-utf-8/issues
Project-URL: Documentation, https://github.com/azzhu/opencv-utf-8
Platform: UNKNOWN
Classifier: Programming Language :: Python :: 3
Classifier: License :: OSI Approved :: MIT License
Classifier: Operating System :: OS Independent
Requires-Python: >=3
Requires-Dist: numpy
Requires-Dist: opencv-python
